{
  "leaders": [
    {
      "name": "BOUCHERIT Hakim",
      "job": "Président",
      "email": "hakim.boucherit@club-internet.fr",
      "number": "0613817772"
    },
    {
      "name": "DIME Bassirou",
      "job": "Secrétaire Général",
      "email": "bass.dime@hotmail.fr",
      "number": "0670222238"
    },
    {
      "name": "LASSERY Sylvain",
      "job": "Trésorier",
      "email": "slassery@gmail.com",
      "number": "0612345678",
      "isEmailDisplayed": false,
      "isNumberDisplayed": false
    },
    {
      "name": "POUA Adrien",
      "job": "Correspondant",
      "img": "/images/staff/dirigeants/poua_adrien.png",
      "email": "argenteuilbasketball@hotmail.fr",
      "number": "0651261379"
    }
  ],
  "coachs": [
    {
      "name": "Benoit",
      "teams": ["Seniors-1", "U11M", "U09M"],
      "email": "b.trichot@live.fr",
      "number": "+33659265041"
    },
    {
      "name": "Soufi",
      "teams": ["Seniors-2"],
      "email": "anabamoha@gmail.com",
      "number": "+33778880396"
    },
    {
      "name": "Sofiane",
      "teams": ["U18F", "U15F", "U13F"],
      "email": "ziane.sofiane95@gmail.com",
      "number": "+33667340253"
    },
    {
      "name": "Allan",
      "teams": ["U17M-1", "U17M-2", "Seniors-Loisirs"],
      "email": "allan.akmo@gmail.com",
      "number": "+33669405738"
    },
    {
      "name": "Yassir",
      "teams": ["U15M-1", "U15M-2"],
      "email": "chajid.yassir@icloud.com",
      "img": "/images/staff/coachs/yassir.png",
      "number": "+33616652219"
    },
    {
      "name": "Jun",
      "teams": ["U13M-1", "U13M-2", "U06"],
      "email": "joobaba8@yahoo.fr",
      "number": "+33660595455"
    },
    {
      "name": "Yassine",
      "teams": ["U11F"],
      "email": "Draouipf.95@gmail.com",
      "number": "+33663692663"
    },
    {
      "name": "Tawfik",
      "teams": ["U13M-2", "U09M"],
      "email": "tawfik3105@gmail.com",
      "number": "+33650268234"
    },
    {
      "name": "Ilyes",
      "teams": ["Seniors-Loisirs", "U13M-2", "U06"],
      "email": "mont.ilyes@yahoo.fr",
      "number": "+33783536725"
    },
    {
      "name": "Samir",
      "teams": ["U09M"],
      "email": "Samir.ait-haddou@outlook.fr",
      "number": "+33781789629"
    }
  ]
}
